{
  "timestamp": "2026-05-12T23:42:06.145320Z",
  "source": "Environment Canada",
  "location": "Crowsnest Pass, AB",
  "conditions": {
    "temperature": 21.1,
    "pressure_kpa": 101.8,
    "pressure_tendency": "falling",
    "humidity_percent": 16,
    "dewpoint": -5.9,
    "wind_speed_kmh": 15,
    "wind_direction": "WNW",
    "condition": "A few clouds",
    "daily_max_gust_kmh": 33
  },
  "daily_stats": {
    "date": "2026-05-12",
    "max_gust_kmh": 33,
    "max_gust_time": "21:43 UTC",
    "high_temp": 21.1,
    "high_temp_time": "23:42 UTC",
    "low_temp": -2.8,
    "low_temp_time": "12:07 UTC"
  },
  "observation_time": "2026-05-12T23:00:00Z",
  "fetch_time_utc": "2026-05-12T23:42:06.145326Z"
}