{
  "timestamp": "2026-02-18T02:07:17.487020Z",
  "source": "Environment Canada",
  "location": "Crowsnest Pass, AB",
  "conditions": {
    "temperature": -16.6,
    "pressure_kpa": 101.0,
    "pressure_tendency": "rising",
    "humidity_percent": 72,
    "dewpoint": -20.4,
    "condition": "Light snow"
  },
  "daily_stats": {
    "date": "2026-02-17",
    "max_gust_kmh": null,
    "max_gust_time": null,
    "high_temp": -2.5,
    "high_temp_time": "07:14 UTC",
    "low_temp": -16.6,
    "low_temp_time": "02:07 UTC"
  },
  "observation_time": "2026-02-18T02:00:00Z",
  "fetch_time_utc": "2026-02-18T02:07:17.487028Z"
}