{
  "fetched_at": "2026-05-22T08:38:39.175451+00:00",
  "forecast": [
    {
      "day": "Friday",
      "condition": "Chance of showers",
      "icon": "\ud83c\udf27\ufe0f",
      "high": 19,
      "low": 6
    },
    {
      "day": "Saturday",
      "condition": "Sunny",
      "icon": "\u2600\ufe0f",
      "high": 22,
      "low": 11
    },
    {
      "day": "Sunday",
      "condition": "Sunny",
      "icon": "\u2600\ufe0f",
      "high": 21,
      "low": 11
    },
    {
      "day": "Monday",
      "condition": "A mix of sun and cloud",
      "icon": "\ud83c\udf28\ufe0f",
      "high": 20,
      "low": 10
    },
    {
      "day": "Tuesday",
      "condition": "Showers",
      "icon": "\ud83c\udf27\ufe0f",
      "high": 20,
      "low": 10
    },
    {
      "day": "Wednesday",
      "condition": "Chance of showers",
      "icon": "\ud83c\udf27\ufe0f",
      "high": 23,
      "low": null
    }
  ]
}