{
  "daily_records": [
    {
      "date": "2026-06-13",
      "high": 16.7,
      "low": 0.7
    },
    {
      "date": "2026-06-12",
      "high": 12.5,
      "low": 6.1
    },
    {
      "date": "2026-06-11",
      "high": 17.4,
      "low": 3.6
    },
    {
      "date": "2026-06-10",
      "high": 15.0,
      "low": 6.0
    },
    {
      "date": "2026-06-09",
      "high": 14.5,
      "low": 5.7
    },
    {
      "date": "2026-06-08",
      "high": 17.2,
      "low": 6.0
    },
    {
      "date": "2026-06-07",
      "high": 11.3,
      "low": 5.2
    }
  ],
  "last_updated": "2026-06-14T18:54:34.429510Z",
  "source": "Environment Canada MSC Datamart - Station 3051R4R"
}